import_scons-2.5.0.dist-info/METADATA
import_scons-2.5.0.dist-info/WHEEL
import_scons-2.5.0.dist-info/entry_points.txt
SCons/Defaults.py
SCons/Errors.py
SCons/Job.py
SCons/Memoize.py
SCons/SConf.py
SCons/Sig.py
SCons/Taskmaster.py
SCons/Warnings.py
SCons/__init__.py
SCons/__main__.py
SCons/Builder.py
SCons/Conftest.py
SCons/dblite.py
SCons/Debug.py
SCons/Environment.py
SCons/Executor.py
SCons/exitfuncs.py
SCons/PathList.py
SCons/SConsign.py
SCons/Subst.py
SCons/Util.py
SCons/Action.py
SCons/CacheDir.py
SCons/cpp.py
SCons/compat/__init__.py
SCons/compat/_scons_dbm.py
SCons/Node/__init__.py
SCons/Node/Alias.py
SCons/Node/FS.py
SCons/Node/Python.py
SCons/Options/BoolOption.py
SCons/Options/EnumOption.py
SCons/Options/ListOption.py
SCons/Options/PackageOption.py
SCons/Options/__init__.py
SCons/Options/PathOption.py
SCons/Platform/__init__.py
SCons/Platform/aix.py
SCons/Platform/cygwin.py
SCons/Platform/darwin.py
SCons/Platform/hpux.py
SCons/Platform/irix.py
SCons/Platform/os2.py
SCons/Platform/posix.py
SCons/Platform/sunos.py
SCons/Platform/win32.py
SCons/Scanner/__init__.py
SCons/Scanner/C.py
SCons/Scanner/D.py
SCons/Scanner/Dir.py
SCons/Scanner/Fortran.py
SCons/Scanner/IDL.py
SCons/Scanner/LaTeX.py
SCons/Scanner/Prog.py
SCons/Scanner/RC.py
SCons/Scanner/SWIG.py
SCons/Script/__init__.py
SCons/Script/Interactive.py
SCons/Script/Main.py
SCons/Script/SConscript.py
SCons/Script/SConsOptions.py
SCons/Tool/sunf95.py
SCons/Tool/sunf90.py
SCons/Tool/suncc.py
SCons/Tool/sunf77.py
SCons/Tool/msvc.py
SCons/Tool/mwld.py
SCons/Tool/masm.py
SCons/Tool/yacc.py
SCons/Tool/mssdk.py
SCons/Tool/msvs.py
SCons/Tool/mwcc.py
SCons/Tool/nasm.py
SCons/Tool/pdf.py
SCons/Tool/pdftex.py
SCons/Tool/Perforce.py
SCons/Tool/RCS.py
SCons/Tool/rmic.py
SCons/Tool/rpm.py
SCons/Tool/sunlink.py
SCons/Tool/sgiar.py
SCons/Tool/tar.py
SCons/Tool/m4.py
SCons/Tool/ar.py
SCons/Tool/msgfmt.py
SCons/Tool/aixlink.py
SCons/Tool/GettextCommon.py
SCons/Tool/msgmerge.py
SCons/Tool/bcc32.py
SCons/Tool/386asm.py
SCons/Tool/aixcc.py
SCons/Tool/BitKeeper.py
SCons/Tool/sgic++.py
SCons/Tool/applelink.py
SCons/Tool/gs.py
SCons/Tool/wix.py
import_scons-2.5.0.dist-info/RECORD